hoardy_mail/__init__.py
hoardy_mail/__main__.py
hoardy_mail/argparse_better.py
hoardy_mail/exceptions.py
hoardy_mail-2.6.2.dist-info/LICENSE.txt
hoardy_mail-2.6.2.dist-info/METADATA
hoardy_mail-2.6.2.dist-info/WHEEL
hoardy_mail-2.6.2.dist-info/entry_points.txt
hoardy_mail-2.6.2.dist-info/top_level.txt
hoardy_mail-2.6.2.dist-info/RECORD
