Metadata-Version: 2.1
Name: hoardy-mail
Version: 2.6.2
Summary: A handy Swiss-army-knife-like utility for fetching, flagging/marking, deleting/expiring, and performing other batch operations on messages residing on IMAP servers
Author-email: Jan Malakhovski <oxij@oxij.org>
License: GPL-3.0-or-later
Project-URL: Homepage, https://oxij.org/software/hoardy-mail/
Project-URL: GitHub, https://github.com/Own-Data-Privateer/hoardy-mail
Project-URL: Support Development, https://oxij.org/#support
Keywords: IMAP,IMAP4,mail,email,e-mail,mail delivery agent,MDA,LDA,fetchmail,getmail,fdm,fetch,archive,download,delete,expire,mark,star,mark as seen,mark as unseen,mark as flagged,mark as unflagged
Classifier: Development Status :: 4 - Beta
Classifier: Programming Language :: Python :: 3
Classifier: License :: OSI Approved :: GNU General Public License v3 or later (GPLv3+)
Classifier: Intended Audience :: End Users/Desktop
Classifier: Topic :: Communications :: Email
Classifier: Topic :: Office/Business
Classifier: Topic :: System :: Archiving
Classifier: Topic :: System :: Archiving :: Backup
Classifier: Topic :: System :: Archiving :: Mirroring
Classifier: Topic :: System :: Recovery Tools
Classifier: Operating System :: POSIX
Classifier: Environment :: Console
Requires-Python: >=3.7
License-File: LICENSE.txt
Requires-Dist: importlib-metadata ; python_version < "3.8"
